jtcmake/__init__.py
jtcmake/core/__init__.py
jtcmake/core/events.py
jtcmake/core/make.py
jtcmake/core/rule.py
jtcmake/frontend/__init__.py
jtcmake/frontend/event_logger.py
jtcmake/frontend/events.py
jtcmake/frontend/file.py
jtcmake/frontend/graphviz.py
jtcmake/frontend/group.py
jtcmake/frontend/igroup.py
jtcmake/frontend/misc.py
jtcmake/frontend/rule.py
jtcmake/logwriter/__init__.py
jtcmake/logwriter/writer.py
jtcmake/utils/__init__.py
jtcmake/utils/nest.py
jtcmake/writer/__init__.py
jtcmake/writer/simplehtmlbuilder.py
jtcmake/writer/writer.py
jtcmake-1.0.0.dist-info/LICENSE
jtcmake-1.0.0.dist-info/METADATA
jtcmake-1.0.0.dist-info/WHEEL
jtcmake-1.0.0.dist-info/top_level.txt
jtcmake-1.0.0.dist-info/RECORD
