Metadata-Version: 2.1
Name: jtcmake
Version: 1.0.0
Summary: Makefile-like light weight build tool for Python
Home-page: https://github.com/sugi-a/omochamake
Author: Amane Sugiyama
Author-email: 42127588+sugi-a@users.noreply.github.com
License: MIT
Classifier: Programming Language :: Python :: 3
Classifier: License :: OSI Approved :: MIT License
Classifier: Operating System :: OS Independent
Requires-Python: >=3.4
License-File: LICENSE
